LICENSE.txt
MANIFEST.in
README.md
setup.py
cython/ekdefunc.cpp
cython/ekdefunc.pyx
ekde/__init__.py
ekde/base.py
ekde/new_whitening_transformer_illustration.py
ekde/whitening_transformer.py
ekde.egg-info/PKG-INFO
ekde.egg-info/SOURCES.txt
ekde.egg-info/dependency_links.txt
ekde.egg-info/requires.txt
ekde.egg-info/top_level.txt
tests/boundary_bias_illustration_1d.py
tests/comparison.py
tests/illustration.py
tests/newtest.py
tests/test_2d.py
tests/test_esnet.py