Metadata-Version: 2.1
Name: ekde
Version: 0.0.8
Summary: Efficient Kernel Density Estimation
Home-page: https://gitlab.inria.fr/fmazy/ekde
Author: François-Rémi Mazy
Author-email: francois-remi.mazy@inria.fr
License: BSD 3-Clause License
Keywords: kernel density estimation kde histograms
Platform: UNKNOWN
Classifier: Development Status :: 1 - Planning
Classifier: Intended Audience :: Science/Research
Classifier: License :: OSI Approved :: BSD License
Classifier: Programming Language :: Python
Classifier: Programming Language :: Python :: 3
Classifier: Programming Language :: Python :: 3.6
Classifier: Programming Language :: Python :: 3.7
Classifier: Programming Language :: Python :: 3.8
Classifier: Programming Language :: Python :: 3.9
Classifier: Programming Language :: Cython
Classifier: Topic :: Scientific/Engineering :: Mathematics
License-File: LICENSE.txt
